[{"Year":2018,"Value":21.7,"GeoCode":null},{"Year":2017,"Value":22.3,"GeoCode":null},{"Year":2016,"Value":22.5,"GeoCode":null},{"Year":2015,"Value":22.7,"GeoCode":null},{"Year":2018,"Value":16.2,"GeoCode":"1.0"},{"Year":2017,"Value":18.2,"GeoCode":"1.0"},{"Year":2016,"Value":17.6,"GeoCode":"1.0"},{"Year":2015,"Value":18.1,"GeoCode":"1.0"},{"Year":2018,"Value":17.3,"GeoCode":"2.0"},{"Year":2017,"Value":18.3,"GeoCode":"2.0"},{"Year":2016,"Value":18.9,"GeoCode":"2.0"},{"Year":2015,"Value":19.5,"GeoCode":"2.0"},{"Year":2018,"Value":22.7,"GeoCode":"3.0"},{"Year":2017,"Value":23.5,"GeoCode":"3.0"},{"Year":2016,"Value":23.8,"GeoCode":"3.0"},{"Year":2015,"Value":23.9,"GeoCode":"3.0"},{"Year":2018,"Value":21.5,"GeoCode":"4.0"},{"Year":2017,"Value":21.3,"GeoCode":"4.0"},{"Year":2016,"Value":21.0,"GeoCode":"4.0"},{"Year":2015,"Value":20.9,"GeoCode":"4.0"},{"Year":2018,"Value":26.0,"GeoCode":"5.0"},{"Year":2017,"Value":26.7,"GeoCode":"5.0"},{"Year":2016,"Value":26.9,"GeoCode":"5.0"},{"Year":2015,"Value":27.2,"GeoCode":"5.0"},{"Year":2018,"Value":19.2,"GeoCode":"6.0"},{"Year":2017,"Value":19.8,"GeoCode":"6.0"},{"Year":2016,"Value":20.5,"GeoCode":"6.0"},{"Year":2015,"Value":19.7,"GeoCode":"6.0"},{"Year":2018,"Value":26.9,"GeoCode":"7.0"},{"Year":2017,"Value":27.5,"GeoCode":"7.0"},{"Year":2016,"Value":28.2,"GeoCode":"7.0"},{"Year":2015,"Value":28.9,"GeoCode":"7.0"},{"Year":2018,"Value":23.5,"GeoCode":"8.0"},{"Year":2017,"Value":23.7,"GeoCode":"8.0"},{"Year":2016,"Value":23.9,"GeoCode":"8.0"},{"Year":2015,"Value":23.4,"GeoCode":"8.0"},{"Year":2018,"Value":24.3,"GeoCode":"9.0"},{"Year":2017,"Value":24.4,"GeoCode":"9.0"},{"Year":2016,"Value":24.6,"GeoCode":"9.0"},{"Year":2015,"Value":24.5,"GeoCode":"9.0"},{"Year":2018,"Value":23.4,"GeoCode":"10.0"},{"Year":2017,"Value":23.9,"GeoCode":"10.0"},{"Year":2016,"Value":24.3,"GeoCode":"10.0"},{"Year":2015,"Value":24.4,"GeoCode":"10.0"},{"Year":2018,"Value":24.0,"GeoCode":"11.0"},{"Year":2017,"Value":24.8,"GeoCode":"11.0"},{"Year":2016,"Value":24.9,"GeoCode":"11.0"},{"Year":2015,"Value":25.2,"GeoCode":"11.0"},{"Year":2018,"Value":18.6,"GeoCode":"12.0"},{"Year":2017,"Value":18.9,"GeoCode":"12.0"},{"Year":2016,"Value":19.1,"GeoCode":"12.0"},{"Year":2015,"Value":19.6,"GeoCode":"12.0"},{"Year":2018,"Value":26.2,"GeoCode":"13.0"},{"Year":2017,"Value":26.3,"GeoCode":"13.0"},{"Year":2016,"Value":26.1,"GeoCode":"13.0"},{"Year":2015,"Value":25.7,"GeoCode":"13.0"},{"Year":2018,"Value":22.9,"GeoCode":"14.0"},{"Year":2017,"Value":23.0,"GeoCode":"14.0"},{"Year":2016,"Value":23.0,"GeoCode":"14.0"},{"Year":2015,"Value":22.2,"GeoCode":"14.0"},{"Year":2018,"Value":20.2,"GeoCode":"15.0"},{"Year":2017,"Value":20.8,"GeoCode":"15.0"},{"Year":2016,"Value":21.2,"GeoCode":"15.0"},{"Year":2015,"Value":21.6,"GeoCode":"15.0"},{"Year":2018,"Value":20.1,"GeoCode":"16.0"},{"Year":2017,"Value":21.0,"GeoCode":"16.0"},{"Year":2016,"Value":20.8,"GeoCode":"16.0"},{"Year":2015,"Value":21.2,"GeoCode":"16.0"},{"Year":2018,"Value":16.7,"GeoCode":"17.0"},{"Year":2017,"Value":17.9,"GeoCode":"17.0"},{"Year":2016,"Value":17.6,"GeoCode":"17.0"},{"Year":2015,"Value":17.8,"GeoCode":"17.0"},{"Year":2018,"Value":21.9,"GeoCode":"18.0"},{"Year":2017,"Value":21.6,"GeoCode":"18.0"},{"Year":2016,"Value":22.3,"GeoCode":"18.0"},{"Year":2015,"Value":22.3,"GeoCode":"18.0"},{"Year":2018,"Value":21.0,"GeoCode":"19.0"},{"Year":2017,"Value":21.6,"GeoCode":"19.0"},{"Year":2016,"Value":21.6,"GeoCode":"19.0"},{"Year":2015,"Value":21.9,"GeoCode":"19.0"}]