[{"Year":2021,"Value":6881,"GeoCode":null},{"Year":2020,"Value":5146,"GeoCode":null},{"Year":2019,"Value":7518,"GeoCode":null},{"Year":2018,"Value":7842,"GeoCode":null},{"Year":2017,"Value":8356,"GeoCode":null},{"Year":2016,"Value":8221,"GeoCode":null},{"Year":2015,"Value":7629,"GeoCode":null},{"Year":2014,"Value":7719,"GeoCode":null},{"Year":2013,"Value":7612,"GeoCode":null},{"Year":2012,"Value":7491,"GeoCode":null},{"Year":2011,"Value":6638,"GeoCode":null},{"Year":2010,"Value":6793,"GeoCode":null},{"Year":2009,"Value":6585,"GeoCode":null},{"Year":2021,"Value":238,"GeoCode":"d1"},{"Year":2020,"Value":246,"GeoCode":"d1"},{"Year":2019,"Value":393,"GeoCode":"d1"},{"Year":2018,"Value":384,"GeoCode":"d1"},{"Year":2017,"Value":486,"GeoCode":"d1"},{"Year":2016,"Value":506,"GeoCode":"d1"},{"Year":2015,"Value":431,"GeoCode":"d1"},{"Year":2014,"Value":438,"GeoCode":"d1"},{"Year":2013,"Value":408,"GeoCode":"d1"},{"Year":2012,"Value":576,"GeoCode":"d1"},{"Year":2011,"Value":493,"GeoCode":"d1"},{"Year":2010,"Value":602,"GeoCode":"d1"},{"Year":2009,"Value":527,"GeoCode":"d1"},{"Year":2021,"Value":203,"GeoCode":"d2"},{"Year":2020,"Value":430,"GeoCode":"d2"},{"Year":2019,"Value":616,"GeoCode":"d2"},{"Year":2018,"Value":569,"GeoCode":"d2"},{"Year":2017,"Value":617,"GeoCode":"d2"},{"Year":2016,"Value":628,"GeoCode":"d2"},{"Year":2015,"Value":603,"GeoCode":"d2"},{"Year":2014,"Value":618,"GeoCode":"d2"},{"Year":2013,"Value":612,"GeoCode":"d2"},{"Year":2012,"Value":547,"GeoCode":"d2"},{"Year":2011,"Value":472,"GeoCode":"d2"},{"Year":2010,"Value":508,"GeoCode":"d2"},{"Year":2009,"Value":494,"GeoCode":"d2"},{"Year":2021,"Value":67,"GeoCode":"d3"},{"Year":2020,"Value":332,"GeoCode":"d3"},{"Year":2019,"Value":650,"GeoCode":"d3"},{"Year":2018,"Value":689,"GeoCode":"d3"},{"Year":2017,"Value":766,"GeoCode":"d3"},{"Year":2016,"Value":711,"GeoCode":"d3"},{"Year":2015,"Value":687,"GeoCode":"d3"},{"Year":2014,"Value":760,"GeoCode":"d3"},{"Year":2013,"Value":749,"GeoCode":"d3"},{"Year":2012,"Value":602,"GeoCode":"d3"},{"Year":2011,"Value":499,"GeoCode":"d3"},{"Year":2010,"Value":596,"GeoCode":"d3"},{"Year":2009,"Value":527,"GeoCode":"d3"},{"Year":2021,"Value":249,"GeoCode":"d4"},{"Year":2020,"Value":355,"GeoCode":"d4"},{"Year":2019,"Value":550,"GeoCode":"d4"},{"Year":2018,"Value":588,"GeoCode":"d4"},{"Year":2017,"Value":557,"GeoCode":"d4"},{"Year":2016,"Value":695,"GeoCode":"d4"},{"Year":2015,"Value":619,"GeoCode":"d4"},{"Year":2014,"Value":594,"GeoCode":"d4"},{"Year":2013,"Value":569,"GeoCode":"d4"},{"Year":2012,"Value":619,"GeoCode":"d4"},{"Year":2011,"Value":595,"GeoCode":"d4"},{"Year":2010,"Value":612,"GeoCode":"d4"},{"Year":2009,"Value":519,"GeoCode":"d4"},{"Year":2021,"Value":185,"GeoCode":"d5"},{"Year":2020,"Value":211,"GeoCode":"d5"},{"Year":2019,"Value":375,"GeoCode":"d5"},{"Year":2018,"Value":395,"GeoCode":"d5"},{"Year":2017,"Value":444,"GeoCode":"d5"},{"Year":2016,"Value":478,"GeoCode":"d5"},{"Year":2015,"Value":481,"GeoCode":"d5"},{"Year":2014,"Value":359,"GeoCode":"d5"},{"Year":2013,"Value":379,"GeoCode":"d5"},{"Year":2012,"Value":454,"GeoCode":"d5"},{"Year":2011,"Value":449,"GeoCode":"d5"},{"Year":2010,"Value":575,"GeoCode":"d5"},{"Year":2009,"Value":459,"GeoCode":"d5"},{"Year":2021,"Value":240,"GeoCode":"d6"},{"Year":2020,"Value":269,"GeoCode":"d6"},{"Year":2019,"Value":403,"GeoCode":"d6"},{"Year":2018,"Value":481,"GeoCode":"d6"},{"Year":2017,"Value":426,"GeoCode":"d6"},{"Year":2016,"Value":907,"GeoCode":"d6"},{"Year":2015,"Value":855,"GeoCode":"d6"},{"Year":2014,"Value":636,"GeoCode":"d6"},{"Year":2013,"Value":621,"GeoCode":"d6"},{"Year":2012,"Value":852,"GeoCode":"d6"},{"Year":2011,"Value":775,"GeoCode":"d6"},{"Year":2010,"Value":768,"GeoCode":"d6"},{"Year":2009,"Value":652,"GeoCode":"d6"},{"Year":2021,"Value":331,"GeoCode":"d7"},{"Year":2020,"Value":343,"GeoCode":"d7"},{"Year":2019,"Value":504,"GeoCode":"d7"},{"Year":2018,"Value":600,"GeoCode":"d7"},{"Year":2017,"Value":565,"GeoCode":"d7"},{"Year":2016,"Value":371,"GeoCode":"d7"},{"Year":2015,"Value":324,"GeoCode":"d7"},{"Year":2014,"Value":453,"GeoCode":"d7"},{"Year":2013,"Value":414,"GeoCode":"d7"},{"Year":2012,"Value":281,"GeoCode":"d7"},{"Year":2011,"Value":273,"GeoCode":"d7"},{"Year":2010,"Value":507,"GeoCode":"d7"},{"Year":2009,"Value":301,"GeoCode":"d7"},{"Year":2021,"Value":304,"GeoCode":"d8"},{"Year":2020,"Value":383,"GeoCode":"d8"},{"Year":2019,"Value":428,"GeoCode":"d8"},{"Year":2018,"Value":465,"GeoCode":"d8"},{"Year":2017,"Value":500,"GeoCode":"d8"},{"Year":2016,"Value":570,"GeoCode":"d8"},{"Year":2015,"Value":517,"GeoCode":"d8"},{"Year":2014,"Value":496,"GeoCode":"d8"},{"Year":2013,"Value":460,"GeoCode":"d8"},{"Year":2012,"Value":505,"GeoCode":"d8"},{"Year":2011,"Value":416,"GeoCode":"d8"},{"Year":2010,"Value":175,"GeoCode":"d8"},{"Year":2009,"Value":376,"GeoCode":"d8"},{"Year":2021,"Value":195,"GeoCode":"d9"},{"Year":2020,"Value":137,"GeoCode":"d9"},{"Year":2019,"Value":269,"GeoCode":"d9"},{"Year":2018,"Value":275,"GeoCode":"d9"},{"Year":2017,"Value":310,"GeoCode":"d9"},{"Year":2016,"Value":398,"GeoCode":"d9"},{"Year":2015,"Value":344,"GeoCode":"d9"},{"Year":2014,"Value":201,"GeoCode":"d9"},{"Year":2013,"Value":229,"GeoCode":"d9"},{"Year":2012,"Value":374,"GeoCode":"d9"},{"Year":2011,"Value":331,"GeoCode":"d9"},{"Year":2010,"Value":183,"GeoCode":"d9"},{"Year":2009,"Value":359,"GeoCode":"d9"},{"Year":2021,"Value":203,"GeoCode":"d10"},{"Year":2020,"Value":459,"GeoCode":"d10"},{"Year":2019,"Value":650,"GeoCode":"d10"},{"Year":2018,"Value":689,"GeoCode":"d10"},{"Year":2017,"Value":759,"GeoCode":"d10"},{"Year":2016,"Value":685,"GeoCode":"d10"},{"Year":2015,"Value":658,"GeoCode":"d10"},{"Year":2014,"Value":635,"GeoCode":"d10"},{"Year":2013,"Value":652,"GeoCode":"d10"},{"Year":2012,"Value":682,"GeoCode":"d10"},{"Year":2011,"Value":505,"GeoCode":"d10"},{"Year":2010,"Value":490,"GeoCode":"d10"},{"Year":2009,"Value":459,"GeoCode":"d10"},{"Year":2021,"Value":358,"GeoCode":"d11"},{"Year":2020,"Value":274,"GeoCode":"d11"},{"Year":2019,"Value":551,"GeoCode":"d11"},{"Year":2018,"Value":552,"GeoCode":"d11"},{"Year":2017,"Value":581,"GeoCode":"d11"},{"Year":2016,"Value":459,"GeoCode":"d11"},{"Year":2015,"Value":419,"GeoCode":"d11"},{"Year":2014,"Value":297,"GeoCode":"d11"},{"Year":2013,"Value":296,"GeoCode":"d11"},{"Year":2012,"Value":311,"GeoCode":"d11"},{"Year":2011,"Value":233,"GeoCode":"d11"},{"Year":2010,"Value":501,"GeoCode":"d11"},{"Year":2009,"Value":336,"GeoCode":"d11"},{"Year":2021,"Value":333,"GeoCode":"d12"},{"Year":2020,"Value":326,"GeoCode":"d12"},{"Year":2019,"Value":451,"GeoCode":"d12"},{"Year":2018,"Value":445,"GeoCode":"d12"},{"Year":2017,"Value":468,"GeoCode":"d12"},{"Year":2016,"Value":400,"GeoCode":"d12"},{"Year":2015,"Value":391,"GeoCode":"d12"},{"Year":2014,"Value":486,"GeoCode":"d12"},{"Year":2013,"Value":477,"GeoCode":"d12"},{"Year":2012,"Value":360,"GeoCode":"d12"},{"Year":2011,"Value":295,"GeoCode":"d12"},{"Year":2010,"Value":291,"GeoCode":"d12"},{"Year":2009,"Value":354,"GeoCode":"d12"},{"Year":2021,"Value":280,"GeoCode":"d13"},{"Year":2020,"Value":323,"GeoCode":"d13"},{"Year":2019,"Value":244,"GeoCode":"d13"},{"Year":2018,"Value":248,"GeoCode":"d13"},{"Year":2017,"Value":252,"GeoCode":"d13"},{"Year":2016,"Value":182,"GeoCode":"d13"},{"Year":2015,"Value":174,"GeoCode":"d13"},{"Year":2014,"Value":242,"GeoCode":"d13"},{"Year":2013,"Value":247,"GeoCode":"d13"},{"Year":2012,"Value":273,"GeoCode":"d13"},{"Year":2011,"Value":247,"GeoCode":"d13"},{"Year":2010,"Value":106,"GeoCode":"d13"},{"Year":2009,"Value":237,"GeoCode":"d13"},{"Year":2021,"Value":35,"GeoCode":"d14"},{"Year":2020,"Value":211,"GeoCode":"d14"},{"Year":2019,"Value":273,"GeoCode":"d14"},{"Year":2018,"Value":321,"GeoCode":"d14"},{"Year":2017,"Value":309,"GeoCode":"d14"},{"Year":2016,"Value":103,"GeoCode":"d14"},{"Year":2015,"Value":93,"GeoCode":"d14"},{"Year":2014,"Value":259,"GeoCode":"d14"},{"Year":2013,"Value":295,"GeoCode":"d14"},{"Year":2012,"Value":75,"GeoCode":"d14"},{"Year":2011,"Value":71,"GeoCode":"d14"},{"Year":2010,"Value":84,"GeoCode":"d14"},{"Year":2009,"Value":55,"GeoCode":"d14"},{"Year":2021,"Value":11,"GeoCode":"d15"},{"Year":2020,"Value":160,"GeoCode":"d15"},{"Year":2019,"Value":367,"GeoCode":"d15"},{"Year":2018,"Value":394,"GeoCode":"d15"},{"Year":2017,"Value":406,"GeoCode":"d15"},{"Year":2016,"Value":454,"GeoCode":"d15"},{"Year":2015,"Value":407,"GeoCode":"d15"},{"Year":2014,"Value":368,"GeoCode":"d15"},{"Year":2013,"Value":354,"GeoCode":"d15"},{"Year":2012,"Value":425,"GeoCode":"d15"},{"Year":2011,"Value":404,"GeoCode":"d15"},{"Year":2010,"Value":265,"GeoCode":"d15"},{"Year":2009,"Value":317,"GeoCode":"d15"},{"Year":2021,"Value":24,"GeoCode":"d16"},{"Year":2020,"Value":360,"GeoCode":"d16"},{"Year":2019,"Value":335,"GeoCode":"d16"},{"Year":2018,"Value":286,"GeoCode":"d16"},{"Year":2017,"Value":343,"GeoCode":"d16"},{"Year":2016,"Value":196,"GeoCode":"d16"},{"Year":2015,"Value":212,"GeoCode":"d16"},{"Year":2014,"Value":293,"GeoCode":"d16"},{"Year":2013,"Value":291,"GeoCode":"d16"},{"Year":2012,"Value":225,"GeoCode":"d16"},{"Year":2011,"Value":181,"GeoCode":"d16"},{"Year":2010,"Value":97,"GeoCode":"d16"},{"Year":2009,"Value":172,"GeoCode":"d16"},{"Year":2021,"Value":214,"GeoCode":"d18"},{"Year":2020,"Value":40,"GeoCode":"d18"},{"Year":2019,"Value":70,"GeoCode":"d18"},{"Year":2018,"Value":78,"GeoCode":"d18"},{"Year":2017,"Value":75,"GeoCode":"d18"},{"Year":2016,"Value":73,"GeoCode":"d18"},{"Year":2015,"Value":66,"GeoCode":"d18"},{"Year":2014,"Value":91,"GeoCode":"d18"},{"Year":2013,"Value":108,"GeoCode":"d18"},{"Year":2012,"Value":68,"GeoCode":"d18"},{"Year":2011,"Value":59,"GeoCode":"d18"},{"Year":2010,"Value":74,"GeoCode":"d18"},{"Year":2009,"Value":82,"GeoCode":"d18"},{"Year":2021,"Value":160,"GeoCode":"d19"},{"Year":2020,"Value":147,"GeoCode":"d19"},{"Year":2019,"Value":160,"GeoCode":"d19"},{"Year":2018,"Value":177,"GeoCode":"d19"},{"Year":2017,"Value":257,"GeoCode":"d19"},{"Year":2016,"Value":202,"GeoCode":"d19"},{"Year":2015,"Value":189,"GeoCode":"d19"},{"Year":2014,"Value":326,"GeoCode":"d19"},{"Year":2013,"Value":279,"GeoCode":"d19"},{"Year":2012,"Value":217,"GeoCode":"d19"},{"Year":2011,"Value":193,"GeoCode":"d19"},{"Year":2010,"Value":196,"GeoCode":"d19"},{"Year":2009,"Value":182,"GeoCode":"d19"},{"Year":2021,"Value":220,"GeoCode":"d171"},{"Year":2020,"Value":24,"GeoCode":"d171"},{"Year":2019,"Value":106,"GeoCode":"d171"},{"Year":2018,"Value":95,"GeoCode":"d171"},{"Year":2017,"Value":103,"GeoCode":"d171"},{"Year":2016,"Value":57,"GeoCode":"d171"},{"Year":2015,"Value":50,"GeoCode":"d171"},{"Year":2014,"Value":52,"GeoCode":"d171"},{"Year":2013,"Value":40,"GeoCode":"d171"},{"Year":2012,"Value":41,"GeoCode":"d171"},{"Year":2011,"Value":42,"GeoCode":"d171"},{"Year":2010,"Value":47,"GeoCode":"d171"},{"Year":2009,"Value":49,"GeoCode":"d171"},{"Year":2021,"Value":220,"GeoCode":"d172"},{"Year":2020,"Value":24,"GeoCode":"d172"},{"Year":2019,"Value":106,"GeoCode":"d172"},{"Year":2018,"Value":95,"GeoCode":"d172"},{"Year":2017,"Value":103,"GeoCode":"d172"},{"Year":2016,"Value":57,"GeoCode":"d172"},{"Year":2015,"Value":50,"GeoCode":"d172"},{"Year":2014,"Value":52,"GeoCode":"d172"},{"Year":2013,"Value":40,"GeoCode":"d172"},{"Year":2012,"Value":41,"GeoCode":"d172"},{"Year":2011,"Value":42,"GeoCode":"d172"},{"Year":2010,"Value":47,"GeoCode":"d172"},{"Year":2009,"Value":49,"GeoCode":"d172"},{"Year":2021,"Value":220,"GeoCode":"d173"},{"Year":2020,"Value":24,"GeoCode":"d173"},{"Year":2019,"Value":106,"GeoCode":"d173"},{"Year":2018,"Value":95,"GeoCode":"d173"},{"Year":2017,"Value":103,"GeoCode":"d173"},{"Year":2016,"Value":57,"GeoCode":"d173"},{"Year":2015,"Value":50,"GeoCode":"d173"},{"Year":2014,"Value":52,"GeoCode":"d173"},{"Year":2013,"Value":40,"GeoCode":"d173"},{"Year":2012,"Value":41,"GeoCode":"d173"},{"Year":2011,"Value":42,"GeoCode":"d173"},{"Year":2010,"Value":47,"GeoCode":"d173"},{"Year":2009,"Value":49,"GeoCode":"d173"},{"Year":2021,"Value":220,"GeoCode":"d174"},{"Year":2020,"Value":24,"GeoCode":"d174"},{"Year":2019,"Value":106,"GeoCode":"d174"},{"Year":2018,"Value":95,"GeoCode":"d174"},{"Year":2017,"Value":103,"GeoCode":"d174"},{"Year":2016,"Value":57,"GeoCode":"d174"},{"Year":2015,"Value":50,"GeoCode":"d174"},{"Year":2014,"Value":52,"GeoCode":"d174"},{"Year":2013,"Value":40,"GeoCode":"d174"},{"Year":2012,"Value":41,"GeoCode":"d174"},{"Year":2011,"Value":42,"GeoCode":"d174"},{"Year":2010,"Value":47,"GeoCode":"d174"},{"Year":2009,"Value":49,"GeoCode":"d174"}]