[{"Year":2021,"Value":8100.45,"GeoCode":null},{"Year":2020,"Value":8114.27,"GeoCode":null},{"Year":2019,"Value":8055.46,"GeoCode":null},{"Year":2018,"Value":8084.0,"GeoCode":null},{"Year":2017,"Value":8014.89,"GeoCode":null},{"Year":2016,"Value":8010.0,"GeoCode":null},{"Year":2015,"Value":7966.11,"GeoCode":null},{"Year":2014,"Value":7966.47,"GeoCode":null},{"Year":2013,"Value":8036.56,"GeoCode":null},{"Year":2012,"Value":8086.75,"GeoCode":null},{"Year":2011,"Value":8099.71,"GeoCode":null},{"Year":2010,"Value":8200.64,"GeoCode":null},{"Year":2009,"Value":8251.2,"GeoCode":null},{"Year":2021,"Value":16288.5,"GeoCode":"d1"},{"Year":2020,"Value":16225.18,"GeoCode":"d1"},{"Year":2019,"Value":16019.25,"GeoCode":"d1"},{"Year":2018,"Value":16131.0,"GeoCode":"d1"},{"Year":2017,"Value":15865.3,"GeoCode":"d1"},{"Year":2016,"Value":15841.0,"GeoCode":"d1"},{"Year":2015,"Value":15665.28,"GeoCode":"d1"},{"Year":2014,"Value":15516.75,"GeoCode":"d1"},{"Year":2013,"Value":15606.7,"GeoCode":"d1"},{"Year":2012,"Value":15603.74,"GeoCode":"d1"},{"Year":2011,"Value":15299.57,"GeoCode":"d1"},{"Year":2010,"Value":15352.83,"GeoCode":"d1"},{"Year":2009,"Value":15340.99,"GeoCode":"d1"},{"Year":2021,"Value":24725.02,"GeoCode":"d2"},{"Year":2020,"Value":24709.44,"GeoCode":"d2"},{"Year":2019,"Value":24589.43,"GeoCode":"d2"},{"Year":2018,"Value":24682.0,"GeoCode":"d2"},{"Year":2017,"Value":24588.32,"GeoCode":"d2"},{"Year":2016,"Value":24468.0,"GeoCode":"d2"},{"Year":2015,"Value":24337.33,"GeoCode":"d2"},{"Year":2014,"Value":24470.61,"GeoCode":"d2"},{"Year":2013,"Value":24718.14,"GeoCode":"d2"},{"Year":2012,"Value":24920.08,"GeoCode":"d2"},{"Year":2011,"Value":24877.96,"GeoCode":"d2"},{"Year":2010,"Value":25337.82,"GeoCode":"d2"},{"Year":2009,"Value":25444.57,"GeoCode":"d2"},{"Year":2021,"Value":24713.85,"GeoCode":"d3"},{"Year":2020,"Value":24789.42,"GeoCode":"d3"},{"Year":2019,"Value":24657.55,"GeoCode":"d3"},{"Year":2018,"Value":24731.0,"GeoCode":"d3"},{"Year":2017,"Value":24586.43,"GeoCode":"d3"},{"Year":2016,"Value":24491.0,"GeoCode":"d3"},{"Year":2015,"Value":24451.0,"GeoCode":"d3"},{"Year":2014,"Value":24498.68,"GeoCode":"d3"},{"Year":2013,"Value":24853.21,"GeoCode":"d3"},{"Year":2012,"Value":25043.92,"GeoCode":"d3"},{"Year":2011,"Value":25060.66,"GeoCode":"d3"},{"Year":2010,"Value":25378.16,"GeoCode":"d3"},{"Year":2009,"Value":25329.47,"GeoCode":"d3"},{"Year":2021,"Value":7383.66,"GeoCode":"d4"},{"Year":2020,"Value":7395.49,"GeoCode":"d4"},{"Year":2019,"Value":7319.51,"GeoCode":"d4"},{"Year":2018,"Value":7286.0,"GeoCode":"d4"},{"Year":2017,"Value":7102.06,"GeoCode":"d4"},{"Year":2016,"Value":7062.0,"GeoCode":"d4"},{"Year":2015,"Value":6972.33,"GeoCode":"d4"},{"Year":2014,"Value":6935.67,"GeoCode":"d4"},{"Year":2013,"Value":6920.25,"GeoCode":"d4"},{"Year":2012,"Value":6904.83,"GeoCode":"d4"},{"Year":2011,"Value":6851.63,"GeoCode":"d4"},{"Year":2010,"Value":6843.54,"GeoCode":"d4"},{"Year":2009,"Value":6791.65,"GeoCode":"d4"},{"Year":2021,"Value":24319.04,"GeoCode":"d5"},{"Year":2020,"Value":24430.67,"GeoCode":"d5"},{"Year":2019,"Value":24225.41,"GeoCode":"d5"},{"Year":2018,"Value":24375.0,"GeoCode":"d5"},{"Year":2017,"Value":24121.73,"GeoCode":"d5"},{"Year":2016,"Value":24084.0,"GeoCode":"d5"},{"Year":2015,"Value":24032.74,"GeoCode":"d5"},{"Year":2014,"Value":24112.47,"GeoCode":"d5"},{"Year":2013,"Value":24495.2,"GeoCode":"d5"},{"Year":2012,"Value":24778.65,"GeoCode":"d5"},{"Year":2011,"Value":24865.59,"GeoCode":"d5"},{"Year":2010,"Value":25373.32,"GeoCode":"d5"},{"Year":2009,"Value":25605.32,"GeoCode":"d5"},{"Year":2021,"Value":18114.52,"GeoCode":"d6"},{"Year":2020,"Value":18100.93,"GeoCode":"d6"},{"Year":2019,"Value":18038.32,"GeoCode":"d6"},{"Year":2018,"Value":18138.0,"GeoCode":"d6"},{"Year":2017,"Value":17936.89,"GeoCode":"d6"},{"Year":2016,"Value":17792.0,"GeoCode":"d6"},{"Year":2015,"Value":17796.29,"GeoCode":"d6"},{"Year":2014,"Value":17975.88,"GeoCode":"d6"},{"Year":2013,"Value":18229.91,"GeoCode":"d6"},{"Year":2012,"Value":18221.05,"GeoCode":"d6"},{"Year":2011,"Value":18247.04,"GeoCode":"d6"},{"Year":2010,"Value":18408.32,"GeoCode":"d6"},{"Year":2009,"Value":18630.45,"GeoCode":"d6"},{"Year":2021,"Value":24731.44,"GeoCode":"d7"},{"Year":2020,"Value":24763.62,"GeoCode":"d7"},{"Year":2019,"Value":24411.65,"GeoCode":"d7"},{"Year":2018,"Value":24456.0,"GeoCode":"d7"},{"Year":2017,"Value":24046.26,"GeoCode":"d7"},{"Year":2016,"Value":24001.0,"GeoCode":"d7"},{"Year":2015,"Value":23943.73,"GeoCode":"d7"},{"Year":2014,"Value":23984.05,"GeoCode":"d7"},{"Year":2013,"Value":24207.53,"GeoCode":"d7"},{"Year":2012,"Value":24504.18,"GeoCode":"d7"},{"Year":2011,"Value":24739.12,"GeoCode":"d7"},{"Year":2010,"Value":25189.07,"GeoCode":"d7"},{"Year":2009,"Value":25545.95,"GeoCode":"d7"},{"Year":2021,"Value":20132.34,"GeoCode":"d8"},{"Year":2020,"Value":20208.93,"GeoCode":"d8"},{"Year":2019,"Value":20114.94,"GeoCode":"d8"},{"Year":2018,"Value":20181.0,"GeoCode":"d8"},{"Year":2017,"Value":19933.33,"GeoCode":"d8"},{"Year":2016,"Value":19914.0,"GeoCode":"d8"},{"Year":2015,"Value":19838.56,"GeoCode":"d8"},{"Year":2014,"Value":19837.18,"GeoCode":"d8"},{"Year":2013,"Value":19932.99,"GeoCode":"d8"},{"Year":2012,"Value":19994.9,"GeoCode":"d8"},{"Year":2011,"Value":20060.96,"GeoCode":"d8"},{"Year":2010,"Value":20278.87,"GeoCode":"d8"},{"Year":2009,"Value":20388.86,"GeoCode":"d8"},{"Year":2021,"Value":17586.58,"GeoCode":"d9"},{"Year":2020,"Value":17729.98,"GeoCode":"d9"},{"Year":2019,"Value":17631.48,"GeoCode":"d9"},{"Year":2018,"Value":17660.0,"GeoCode":"d9"},{"Year":2017,"Value":17497.55,"GeoCode":"d9"},{"Year":2016,"Value":17509.0,"GeoCode":"d9"},{"Year":2015,"Value":17402.74,"GeoCode":"d9"},{"Year":2014,"Value":17428.2,"GeoCode":"d9"},{"Year":2013,"Value":17554.17,"GeoCode":"d9"},{"Year":2012,"Value":17716.33,"GeoCode":"d9"},{"Year":2011,"Value":17770.61,"GeoCode":"d9"},{"Year":2010,"Value":18082.19,"GeoCode":"d9"},{"Year":2009,"Value":18202.47,"GeoCode":"d9"},{"Year":2021,"Value":6561.29,"GeoCode":"d10"},{"Year":2020,"Value":6579.84,"GeoCode":"d10"},{"Year":2019,"Value":6526.59,"GeoCode":"d10"},{"Year":2018,"Value":6544.0,"GeoCode":"d10"},{"Year":2017,"Value":6513.0,"GeoCode":"d10"},{"Year":2016,"Value":6504.0,"GeoCode":"d10"},{"Year":2015,"Value":6451.02,"GeoCode":"d10"},{"Year":2014,"Value":6437.69,"GeoCode":"d10"},{"Year":2013,"Value":6456.76,"GeoCode":"d10"},{"Year":2012,"Value":6503.46,"GeoCode":"d10"},{"Year":2011,"Value":6516.53,"GeoCode":"d10"},{"Year":2010,"Value":6625.04,"GeoCode":"d10"},{"Year":2009,"Value":6696.73,"GeoCode":"d10"},{"Year":2021,"Value":14057.39,"GeoCode":"d11"},{"Year":2020,"Value":14048.57,"GeoCode":"d11"},{"Year":2019,"Value":14078.32,"GeoCode":"d11"},{"Year":2018,"Value":14351.0,"GeoCode":"d11"},{"Year":2017,"Value":14273.57,"GeoCode":"d11"},{"Year":2016,"Value":14512.0,"GeoCode":"d11"},{"Year":2015,"Value":14542.44,"GeoCode":"d11"},{"Year":2014,"Value":14588.56,"GeoCode":"d11"},{"Year":2013,"Value":14751.34,"GeoCode":"d11"},{"Year":2012,"Value":14912.87,"GeoCode":"d11"},{"Year":2011,"Value":14991.49,"GeoCode":"d11"},{"Year":2010,"Value":15158.81,"GeoCode":"d11"},{"Year":2009,"Value":15264.4,"GeoCode":"d11"},{"Year":2021,"Value":27872.9,"GeoCode":"d12"},{"Year":2020,"Value":27834.46,"GeoCode":"d12"},{"Year":2019,"Value":27649.01,"GeoCode":"d12"},{"Year":2018,"Value":27850.0,"GeoCode":"d12"},{"Year":2017,"Value":27590.6,"GeoCode":"d12"},{"Year":2016,"Value":27506.0,"GeoCode":"d12"},{"Year":2015,"Value":27259.44,"GeoCode":"d12"},{"Year":2014,"Value":27136.52,"GeoCode":"d12"},{"Year":2013,"Value":27348.14,"GeoCode":"d12"},{"Year":2012,"Value":27408.12,"GeoCode":"d12"},{"Year":2011,"Value":27462.19,"GeoCode":"d12"},{"Year":2010,"Value":27661.13,"GeoCode":"d12"},{"Year":2009,"Value":27642.97,"GeoCode":"d12"},{"Year":2021,"Value":12297.29,"GeoCode":"d13"},{"Year":2020,"Value":12387.52,"GeoCode":"d13"},{"Year":2019,"Value":12405.77,"GeoCode":"d13"},{"Year":2018,"Value":12561.0,"GeoCode":"d13"},{"Year":2017,"Value":12439.73,"GeoCode":"d13"},{"Year":2016,"Value":12489.0,"GeoCode":"d13"},{"Year":2015,"Value":12495.81,"GeoCode":"d13"},{"Year":2014,"Value":12533.42,"GeoCode":"d13"},{"Year":2013,"Value":12710.4,"GeoCode":"d13"},{"Year":2012,"Value":12902.49,"GeoCode":"d13"},{"Year":2011,"Value":12991.48,"GeoCode":"d13"},{"Year":2010,"Value":13314.2,"GeoCode":"d13"},{"Year":2009,"Value":13535.84,"GeoCode":"d13"},{"Year":2021,"Value":18197.33,"GeoCode":"d14"},{"Year":2020,"Value":18268.02,"GeoCode":"d14"},{"Year":2019,"Value":18288.4,"GeoCode":"d14"},{"Year":2018,"Value":18526.0,"GeoCode":"d14"},{"Year":2017,"Value":17676.56,"GeoCode":"d14"},{"Year":2016,"Value":17712.0,"GeoCode":"d14"},{"Year":2015,"Value":17573.07,"GeoCode":"d14"},{"Year":2014,"Value":17608.38,"GeoCode":"d14"},{"Year":2013,"Value":17681.43,"GeoCode":"d14"},{"Year":2012,"Value":17903.61,"GeoCode":"d14"},{"Year":2011,"Value":18139.81,"GeoCode":"d14"},{"Year":2010,"Value":18410.09,"GeoCode":"d14"},{"Year":2009,"Value":18643.23,"GeoCode":"d14"},{"Year":2021,"Value":20591.81,"GeoCode":"d15"},{"Year":2020,"Value":20631.0,"GeoCode":"d15"},{"Year":2019,"Value":20378.78,"GeoCode":"d15"},{"Year":2018,"Value":20352.0,"GeoCode":"d15"},{"Year":2017,"Value":20084.7,"GeoCode":"d15"},{"Year":2016,"Value":20079.0,"GeoCode":"d15"},{"Year":2015,"Value":19873.81,"GeoCode":"d15"},{"Year":2014,"Value":19793.88,"GeoCode":"d15"},{"Year":2013,"Value":20039.02,"GeoCode":"d15"},{"Year":2012,"Value":20155.12,"GeoCode":"d15"},{"Year":2011,"Value":20196.61,"GeoCode":"d15"},{"Year":2010,"Value":20499.23,"GeoCode":"d15"},{"Year":2009,"Value":20696.78,"GeoCode":"d15"},{"Year":2021,"Value":21384.53,"GeoCode":"d16"},{"Year":2020,"Value":21400.78,"GeoCode":"d16"},{"Year":2019,"Value":21074.95,"GeoCode":"d16"},{"Year":2018,"Value":20922.0,"GeoCode":"d16"},{"Year":2017,"Value":20549.97,"GeoCode":"d16"},{"Year":2016,"Value":20470.0,"GeoCode":"d16"},{"Year":2015,"Value":20231.62,"GeoCode":"d16"},{"Year":2014,"Value":20102.39,"GeoCode":"d16"},{"Year":2013,"Value":20209.1,"GeoCode":"d16"},{"Year":2012,"Value":20190.19,"GeoCode":"d16"},{"Year":2011,"Value":20065.01,"GeoCode":"d16"},{"Year":2010,"Value":20083.92,"GeoCode":"d16"},{"Year":2009,"Value":20120.4,"GeoCode":"d16"},{"Year":2021,"Value":7231.75,"GeoCode":"d18"},{"Year":2020,"Value":7250.15,"GeoCode":"d18"},{"Year":2019,"Value":7153.69,"GeoCode":"d18"},{"Year":2018,"Value":7010.0,"GeoCode":"d18"},{"Year":2017,"Value":6988.96,"GeoCode":"d18"},{"Year":2016,"Value":6983.0,"GeoCode":"d18"},{"Year":2015,"Value":6970.99,"GeoCode":"d18"},{"Year":2014,"Value":6998.44,"GeoCode":"d18"},{"Year":2013,"Value":7080.78,"GeoCode":"d18"},{"Year":2012,"Value":7087.77,"GeoCode":"d18"},{"Year":2011,"Value":7103.74,"GeoCode":"d18"},{"Year":2010,"Value":7160.13,"GeoCode":"d18"},{"Year":2009,"Value":7139.67,"GeoCode":"d18"},{"Year":2021,"Value":654.44,"GeoCode":"d19"},{"Year":2020,"Value":648.85,"GeoCode":"d19"},{"Year":2019,"Value":636.73,"GeoCode":"d19"},{"Year":2018,"Value":630.0,"GeoCode":"d19"},{"Year":2017,"Value":627.28,"GeoCode":"d19"},{"Year":2016,"Value":627.0,"GeoCode":"d19"},{"Year":2015,"Value":622.94,"GeoCode":"d19"},{"Year":2014,"Value":625.89,"GeoCode":"d19"},{"Year":2013,"Value":637.51,"GeoCode":"d19"},{"Year":2012,"Value":637.36,"GeoCode":"d19"},{"Year":2011,"Value":633.27,"GeoCode":"d19"},{"Year":2010,"Value":634.97,"GeoCode":"d19"},{"Year":2009,"Value":641.57,"GeoCode":"d19"},{"Year":2021,"Value":438.07,"GeoCode":"d171"},{"Year":2020,"Value":433.14,"GeoCode":"d171"},{"Year":2019,"Value":432.08,"GeoCode":"d171"},{"Year":2018,"Value":431.0,"GeoCode":"d171"},{"Year":2017,"Value":430.05,"GeoCode":"d171"},{"Year":2016,"Value":430.0,"GeoCode":"d171"},{"Year":2015,"Value":426.3,"GeoCode":"d171"},{"Year":2014,"Value":424.98,"GeoCode":"d171"},{"Year":2013,"Value":426.43,"GeoCode":"d171"},{"Year":2012,"Value":426.76,"GeoCode":"d171"},{"Year":2011,"Value":433.86,"GeoCode":"d171"},{"Year":2010,"Value":434.32,"GeoCode":"d171"},{"Year":2009,"Value":432.94,"GeoCode":"d171"},{"Year":2021,"Value":438.07,"GeoCode":"d172"},{"Year":2020,"Value":433.14,"GeoCode":"d172"},{"Year":2019,"Value":432.08,"GeoCode":"d172"},{"Year":2018,"Value":431.0,"GeoCode":"d172"},{"Year":2017,"Value":430.05,"GeoCode":"d172"},{"Year":2016,"Value":430.0,"GeoCode":"d172"},{"Year":2015,"Value":426.3,"GeoCode":"d172"},{"Year":2014,"Value":424.98,"GeoCode":"d172"},{"Year":2013,"Value":426.43,"GeoCode":"d172"},{"Year":2012,"Value":426.76,"GeoCode":"d172"},{"Year":2011,"Value":433.86,"GeoCode":"d172"},{"Year":2010,"Value":434.32,"GeoCode":"d172"},{"Year":2009,"Value":432.94,"GeoCode":"d172"},{"Year":2021,"Value":438.07,"GeoCode":"d173"},{"Year":2020,"Value":433.14,"GeoCode":"d173"},{"Year":2019,"Value":432.08,"GeoCode":"d173"},{"Year":2018,"Value":431.0,"GeoCode":"d173"},{"Year":2017,"Value":430.05,"GeoCode":"d173"},{"Year":2016,"Value":430.0,"GeoCode":"d173"},{"Year":2015,"Value":426.3,"GeoCode":"d173"},{"Year":2014,"Value":424.98,"GeoCode":"d173"},{"Year":2013,"Value":426.43,"GeoCode":"d173"},{"Year":2012,"Value":426.76,"GeoCode":"d173"},{"Year":2011,"Value":433.86,"GeoCode":"d173"},{"Year":2010,"Value":434.32,"GeoCode":"d173"},{"Year":2009,"Value":432.94,"GeoCode":"d173"},{"Year":2021,"Value":438.07,"GeoCode":"d174"},{"Year":2020,"Value":433.14,"GeoCode":"d174"},{"Year":2019,"Value":432.08,"GeoCode":"d174"},{"Year":2018,"Value":431.0,"GeoCode":"d174"},{"Year":2017,"Value":430.05,"GeoCode":"d174"},{"Year":2016,"Value":430.0,"GeoCode":"d174"},{"Year":2015,"Value":426.3,"GeoCode":"d174"},{"Year":2014,"Value":424.98,"GeoCode":"d174"},{"Year":2013,"Value":426.43,"GeoCode":"d174"},{"Year":2012,"Value":426.76,"GeoCode":"d174"},{"Year":2011,"Value":433.86,"GeoCode":"d174"},{"Year":2010,"Value":434.32,"GeoCode":"d174"},{"Year":2009,"Value":432.94,"GeoCode":"d174"}]