[{"Year":2019,"Value":12385.27},{"Year":2018,"Value":12446.88},{"Year":2017,"Value":12279.95},{"Year":2016,"Value":12043.63},{"Year":2015,"Value":11595.71},{"Year":2014,"Value":11058.88},{"Year":2013,"Value":10659.04},{"Year":2012,"Value":11870.0},{"Year":2011,"Value":11643.61},{"Year":2010,"Value":11950.56},{"Year":2009,"Value":12101.51},{"Year":2019,"Value":550.72},{"Year":2018,"Value":476.37},{"Year":2017,"Value":447.53},{"Year":2016,"Value":355.1},{"Year":2015,"Value":377.64},{"Year":2014,"Value":365.0},{"Year":2013,"Value":371.54},{"Year":2012,"Value":321.6},{"Year":2011,"Value":384.39},{"Year":2010,"Value":272.8},{"Year":2009,"Value":318.88},{"Year":2019,"Value":4.45},{"Year":2018,"Value":3.83},{"Year":2017,"Value":3.64},{"Year":2016,"Value":2.95},{"Year":2015,"Value":3.26},{"Year":2014,"Value":3.3},{"Year":2013,"Value":3.49},{"Year":2012,"Value":2.71},{"Year":2011,"Value":3.3},{"Year":2010,"Value":2.28},{"Year":2009,"Value":2.64}]